{
    "title": "titanic-logistic-regression-with-python",
    "notebook": "/src/notebooks/kaggle/mnassrib-titanic-logistic-regression-with-python/titanic-logistic-regression-with-python.ipynb",
    "metadata": "/src/notebooks/kaggle/mnassrib-titanic-logistic-regression-with-python/titanic-logistic-regression-with-python.toml",
    "metrics": {
        "nb_code_cells": 39,
        "nb_markdown_cells": 44,
        "dependencies_installation_detected": false,
        "code_quality": {
            "pylint_score": {
                "score": 4.844961240310077,
                "count_by_severity": {
                    "convention": 102,
                    "error": 5,
                    "fatal": 0,
                    "info": 0,
                    "refactor": 0,
                    "statement": 258,
                    "warning": 6
                },
                "count_by_messages": {
                    "trailing-whitespace": 23,
                    "line-too-long": 14,
                    "trailing-newlines": 1,
                    "missing-module-docstring": 1,
                    "wrong-import-position": 13,
                    "consider-using-f-string": 46,
                    "too-many-function-args": 5,
                    "invalid-name": 2,
                    "wrong-import-order": 1,
                    "ungrouped-imports": 1,
                    "unused-import": 6
                }
            },
            "mypy_score": {
                "score": -1,
                "count_by_severity": {},
                "count_by_messages": {}
            }
        }
    },
    "profile": [
        {
            "cell_type": "markdown",
            "nb_lines": 1778
        },
        {
            "cell_type": "markdown",
            "nb_lines": 51
        },
        {
            "cell_type": "code",
            "nb_lines": 320
        },
        {
            "cell_type": "code",
            "nb_lines": 209
        },
        {
            "cell_type": "code",
            "nb_lines": 83
        },
        {
            "cell_type": "code",
            "nb_lines": 34
        },
        {
            "cell_type": "code",
            "nb_lines": 81
        },
        {
            "cell_type": "markdown",
            "nb_lines": 222
        },
        {
            "cell_type": "markdown",
            "nb_lines": 61
        },
        {
            "cell_type": "code",
            "nb_lines": 60
        },
        {
            "cell_type": "markdown",
            "nb_lines": 50
        },
        {
            "cell_type": "code",
            "nb_lines": 137
        },
        {
            "cell_type": "markdown",
            "nb_lines": 103
        },
        {
            "cell_type": "code",
            "nb_lines": 187
        },
        {
            "cell_type": "markdown",
            "nb_lines": 193
        },
        {
            "cell_type": "code",
            "nb_lines": 171
        },
        {
            "cell_type": "markdown",
            "nb_lines": 49
        },
        {
            "cell_type": "code",
            "nb_lines": 143
        },
        {
            "cell_type": "markdown",
            "nb_lines": 168
        },
        {
            "cell_type": "markdown",
            "nb_lines": 52
        },
        {
            "cell_type": "code",
            "nb_lines": 152
        },
        {
            "cell_type": "markdown",
            "nb_lines": 118
        },
        {
            "cell_type": "code",
            "nb_lines": 221
        },
        {
            "cell_type": "code",
            "nb_lines": 106
        },
        {
            "cell_type": "markdown",
            "nb_lines": 89
        },
        {
            "cell_type": "markdown",
            "nb_lines": 67
        },
        {
            "cell_type": "markdown",
            "nb_lines": 482
        },
        {
            "cell_type": "code",
            "nb_lines": 241
        },
        {
            "cell_type": "code",
            "nb_lines": 71
        },
        {
            "cell_type": "code",
            "nb_lines": 47
        },
        {
            "cell_type": "code",
            "nb_lines": 400
        },
        {
            "cell_type": "markdown",
            "nb_lines": 51
        },
        {
            "cell_type": "markdown",
            "nb_lines": 293
        },
        {
            "cell_type": "code",
            "nb_lines": 230
        },
        {
            "cell_type": "markdown",
            "nb_lines": 119
        },
        {
            "cell_type": "code",
            "nb_lines": 360
        },
        {
            "cell_type": "markdown",
            "nb_lines": 490
        },
        {
            "cell_type": "code",
            "nb_lines": 22
        },
        {
            "cell_type": "code",
            "nb_lines": 702
        },
        {
            "cell_type": "markdown",
            "nb_lines": 47
        },
        {
            "cell_type": "markdown",
            "nb_lines": 45
        },
        {
            "cell_type": "code",
            "nb_lines": 380
        },
        {
            "cell_type": "markdown",
            "nb_lines": 261
        },
        {
            "cell_type": "code",
            "nb_lines": 218
        },
        {
            "cell_type": "markdown",
            "nb_lines": 123
        },
        {
            "cell_type": "code",
            "nb_lines": 122
        },
        {
            "cell_type": "markdown",
            "nb_lines": 46
        },
        {
            "cell_type": "code",
            "nb_lines": 385
        },
        {
            "cell_type": "markdown",
            "nb_lines": 320
        },
        {
            "cell_type": "markdown",
            "nb_lines": 57
        },
        {
            "cell_type": "code",
            "nb_lines": 82
        },
        {
            "cell_type": "markdown",
            "nb_lines": 57
        },
        {
            "cell_type": "markdown",
            "nb_lines": 55
        },
        {
            "cell_type": "code",
            "nb_lines": 75
        },
        {
            "cell_type": "markdown",
            "nb_lines": 804
        },
        {
            "cell_type": "markdown",
            "nb_lines": 73
        },
        {
            "cell_type": "code",
            "nb_lines": 92
        },
        {
            "cell_type": "markdown",
            "nb_lines": 185
        },
        {
            "cell_type": "markdown",
            "nb_lines": 57
        },
        {
            "cell_type": "code",
            "nb_lines": 76
        },
        {
            "cell_type": "markdown",
            "nb_lines": 100
        },
        {
            "cell_type": "markdown",
            "nb_lines": 53
        },
        {
            "cell_type": "markdown",
            "nb_lines": 772
        },
        {
            "cell_type": "code",
            "nb_lines": 526
        },
        {
            "cell_type": "markdown",
            "nb_lines": 362
        },
        {
            "cell_type": "code",
            "nb_lines": 681
        },
        {
            "cell_type": "markdown",
            "nb_lines": 38
        },
        {
            "cell_type": "code",
            "nb_lines": 264
        },
        {
            "cell_type": "markdown",
            "nb_lines": 946
        },
        {
            "cell_type": "markdown",
            "nb_lines": 117
        },
        {
            "cell_type": "code",
            "nb_lines": 2038
        },
        {
            "cell_type": "markdown",
            "nb_lines": 117
        },
        {
            "cell_type": "code",
            "nb_lines": 847
        },
        {
            "cell_type": "markdown",
            "nb_lines": 116
        },
        {
            "cell_type": "code",
            "nb_lines": 780
        },
        {
            "cell_type": "markdown",
            "nb_lines": 67
        },
        {
            "cell_type": "code",
            "nb_lines": 872
        },
        {
            "cell_type": "markdown",
            "nb_lines": 195
        },
        {
            "cell_type": "markdown",
            "nb_lines": 88
        },
        {
            "cell_type": "code",
            "nb_lines": 2309
        },
        {
            "cell_type": "markdown",
            "nb_lines": 390
        },
        {
            "cell_type": "code",
            "nb_lines": 3198
        },
        {
            "cell_type": "code",
            "nb_lines": 244
        }
    ]
}