{
    "title": "data-cleaning-challenge-scale-and-normalize-data",
    "notebook": "/src/notebooks/kaggle/rtatman-data-cleaning-challenge-scale-and-normalize-data/data-cleaning-challenge-scale-and-normalize-data.ipynb",
    "metadata": "/src/notebooks/kaggle/rtatman-data-cleaning-challenge-scale-and-normalize-data/data-cleaning-challenge-scale-and-normalize-data.toml",
    "metrics": {
        "nb_code_cells": 7,
        "nb_markdown_cells": 11,
        "dependencies_installation_detected": false,
        "code_quality": {
            "pylint_score": {
                "score": 8.61111111111111,
                "count_by_severity": {
                    "convention": 5,
                    "error": 0,
                    "fatal": 0,
                    "info": 0,
                    "refactor": 0,
                    "statement": 36,
                    "warning": 0
                },
                "count_by_messages": {
                    "trailing-whitespace": 2,
                    "line-too-long": 1,
                    "trailing-newlines": 1,
                    "missing-module-docstring": 1
                }
            },
            "mypy_score": {
                "score": -1,
                "count_by_severity": {},
                "count_by_messages": {}
            }
        }
    },
    "profile": [
        {
            "cell_type": "markdown",
            "nb_lines": 2043
        },
        {
            "cell_type": "markdown",
            "nb_lines": 218
        },
        {
            "cell_type": "code",
            "nb_lines": 420
        },
        {
            "cell_type": "markdown",
            "nb_lines": 146
        },
        {
            "cell_type": "markdown",
            "nb_lines": 1962
        },
        {
            "cell_type": "code",
            "nb_lines": 424
        },
        {
            "cell_type": "markdown",
            "nb_lines": 1337
        },
        {
            "cell_type": "code",
            "nb_lines": 298
        },
        {
            "cell_type": "markdown",
            "nb_lines": 1113
        },
        {
            "cell_type": "markdown",
            "nb_lines": 327
        },
        {
            "cell_type": "code",
            "nb_lines": 398
        },
        {
            "cell_type": "markdown",
            "nb_lines": 179
        },
        {
            "cell_type": "code",
            "nb_lines": 90
        },
        {
            "cell_type": "markdown",
            "nb_lines": 144
        },
        {
            "cell_type": "code",
            "nb_lines": 582
        },
        {
            "cell_type": "markdown",
            "nb_lines": 100
        },
        {
            "cell_type": "code",
            "nb_lines": 119
        },
        {
            "cell_type": "markdown",
            "nb_lines": 1322
        }
    ]
}